Edgepulse/__init__.py
Edgepulse/core.py
Edgepulse/py.typed
edgepulse-0.1.2.dist-info/licenses/LICENSE
edgepulse-0.1.2.dist-info/METADATA
edgepulse-0.1.2.dist-info/WHEEL
edgepulse-0.1.2.dist-info/top_level.txt
edgepulse-0.1.2.dist-info/RECORD
