Metadata-Version: 2.4
Name: edgepulse
Version: 0.1.2
Summary: EdgePulse Python SDK for edge functions monitoring and observability
Author-email: Jeremy Trips <jeremy.trips@gmail.com>
Maintainer-email: Jeremy Trips <jeremy.trips@gmail.com>
License: MIT
Project-URL: Homepage, https://github.com/edgepulse/sdk-python
Project-URL: Documentation, https://docs.edgepulse.com/sdk/python
Project-URL: Repository, https://github.com/edgepulse/sdk-python.git
Project-URL: Issues, https://github.com/edgepulse/sdk-python/issues
Project-URL: Changelog, https://github.com/edgepulse/sdk-python/blob/main/CHANGELOG.md
Keywords: monitoring,observability,telemetry,performance,tracking
Classifier: Development Status :: 3 - Alpha
Classifier: Intended Audience :: Developers
Classifier: License :: OSI Approved :: MIT License
Classifier: Operating System :: OS Independent
Classifier: Programming Language :: Python :: 3
Classifier: Programming Language :: Python :: 3.9
Classifier: Programming Language :: Python :: 3.10
Classifier: Programming Language :: Python :: 3.11
Classifier: Programming Language :: Python :: 3.12
Classifier: Topic :: Software Development :: Libraries :: Python Modules
Classifier: Topic :: System :: Monitoring
Requires-Python: >=3.9
License-File: LICENSE
Provides-Extra: dev
Requires-Dist: pytest>=6.0; extra == "dev"
Requires-Dist: pytest-cov>=2.0; extra == "dev"
Requires-Dist: black>=22.0; extra == "dev"
Requires-Dist: isort>=5.0; extra == "dev"
Requires-Dist: mypy>=0.900; extra == "dev"
Requires-Dist: flake8>=4.0; extra == "dev"
Dynamic: license-file
